{
	"$schema": "https://schemas.wp.org/trunk/block.json",
	"apiVersion": 3,
	"name": "chubes-games/ai-adventure-step",
	"version": "0.1.0",
	"title": "AI Adventure Step",
	"category": "widgets",
	"icon": "smiley",
	"description": "Example block scaffolded with Create Block tool – no build step required.",
	"example": {},
	"supports": {
		"html": false
	},
	"attributes": {
		"label": {
			"type": "string",
			"source": "html",
			"selector": "h4"
		},
		"stepPrompt": {
			"type": "string",
			"source": "html",
			"selector": ".ai-adventure-step-prompt"
		},
		"stepId": {
			"type": "string"
		},
		"triggers": {
			"type": "array",
			"default": []
		}
	},
	"parent": [ "chubes-games/ai-adventure-path" ],
	"textdomain": "ai-adventure-step",
	"editorScript": "file:../../build/ai-adventure-step/index.js",
	"editorStyle": "file:../../build/ai-adventure-step/editor.css"
}